ricetypes/IMNS.py
ricetypes/__init__.py
ricetypes-0.1.7.dist-info/METADATA
ricetypes-0.1.7.dist-info/WHEEL
ricetypes-0.1.7.dist-info/top_level.txt
ricetypes-0.1.7.dist-info/RECORD
