Metadata-Version: 2.2
Name: ricetypes
Version: 0.1.7
Summary: Some nice type like things
Author-email: Maxwell Gisborne <maxwell.gisborne@plymouth.ac.uk>
License: MIT License
Project-URL: Homepage, https://github.com/maxwell-gisborne/nicetypes
Keywords: typing,result,option,enum
Requires-Python: >=3.9
